Workbook

Sheet Instructions
A1: Infosys (INFY.NS) — DCF Valuation Model
A2: Template built from historical filings + public data (Sept 2026). Refresh before real use.
A5: HOW THIS WORKBOOK IS ORGANIZED
A6: 1. Historicals | B6: Actual reported financials, FY2022–FY2026. Source noted per row.
A7: 2. Assumptions | B7: Every lever the model uses. Change numbers ONLY on this tab.
A8: 3. Forecast | B8: 5-year projection (FY2027–FY2031), built entirely from Assumptions.
A9: 4. WACC
A10: 5. DCF
A12: COLOR LEGEND
A13: Blue text | B13: Hardcoded input — a real number typed in, not calculated.
A14: Black text | B14: Formula — calculated from other cells.
A15: Green text | B15: Link pulling a value from another sheet.
A16: Yellow fill | B16: Cells you should REVIEW/UPDATE before trusting the output — see notes below.
A18: BEFORE YOU RELY ON THIS MODEL — REFRESH THESE (all yellow-filled cells)
A19: Current share price | B19: Assumptions!B21 — pull live from NSE/yfinance.
A20: Risk-free rate | B20: Assumptions!B17 — current 10Y India G-Sec yield (investing.com / RBI).
A21: Equity risk premium | B21: Assumptions!B18 — Damodaran's India ERP estimate, updated yearly.
A22: Beta | B22: Assumptions!B19 — recompute from 2–5yr weekly returns vs NIFTY 50, or pull via yfinance.
A23: Cost of debt | B23: Assumptions!B20 — Infosys's actual interest expense ÷ total debt, latest annual report.
A24: Historicals | B24: All of tab 2 — re-run data_pull.py to replace with the latest 5 filed years.
A26: WHAT THIS MODEL DELIBERATELY DOES NOT DO (be ready to explain why, or add later)
A27: No sensitivity table yet | B27: Single-point WACC / terminal growth. Good v2 addition: WACC x g grid.
A28: Only Gordon Growth terminal value | B28: Exit-multiple method would be a good cross-check to add.
A29: Flat margin assumption | B29: Real model would build cost lines up (S&A, R&D) rather than one EBIT margin %.
A30: Manual data refresh | B30: Historicals are pasted from a Python pull, not live-linked.

Sheet Historicals
A1: Historicals — Infosys Consolidated (IFRS)
A2: All figures in ₹ Crores unless noted. Source: Infosys Annual Reports / Investor filings, compiled Sept 2026.
A4: Line Item (₹ Crores) | B4: FY2022 | C4: FY2023 | D4: FY2024 | E4: FY2025 | F4: FY2026
A5: Total Revenue | B5: 123936 | C5: 149468 | D5: 158381 | E5: 166590 | F5: 182972
A6: Total Operating Expenses | B6: 93826 | C6: 116146 | D6: 122393 | E6: 128982 | F6: 141688
A7: Operating Profit (EBIT) | B7: 30310 | C7: 33606 | D7: 36458 | E7: 38024 | F7: 41700
A8: Profit Before Tax | B8: 30110 | C8: 33322 | D8: 35988 | E8: 37608 | F8: 39995
A9: Net Income (PAT) | B9: 22146 | C9: 24108 | D9: 26248 | E9: 26750 | F9: 29474
A10: Total Assets | B10: 117885 | C10: 125816 | D10: 137814 | E10: 148903 | F10: 155967
A11: Total Shareholders' Equity | B11: 75350 | C11: 75407 | D11: 88116 | E11: 95818 | F11: 92852
A12: Total Debt (incl. lease liabilities) | B12: 4000 | C12: 4266 | D12: 3766 | E12: 3459 | F12: 3749
A13: Cash & Cash Equivalents | C13: 6534 | D13: 8191 | E13: 14265 | F13: 8727
A14: Capital Expenditure (approx.) | B14: 2407 | C14: 2648 | D14: 2208 | E14: 2183 | F14: 2540
A16: Shares Outstanding (Crores) | B16: 414
A18: Revenue Growth % (YoY) | C18: =C5/B5-1 -> 0.20600955 | D18: =D5/C5-1 -> 0.059631493 | E18: =E5/D5-1 -> 0.051830712 | F18: =F5/E5-1 -> 0.098337235
A19: EBIT Margin % | B19: =B7/B5 -> 0.24456171 | C19: =C7/C5 -> 0.22483742 | D19: =D7/D5 -> 0.23019175 | E19: =E7/E5 -> 0.22824899 | F19: =F7/F5 -> 0.22790372
A20: Effective Tax Rate % | B20: =(B8-B9)/B8 -> 0.26449684 | C20: =(C8-C9)/C8 -> 0.27651401 | D20: =(D8-D9)/D8 -> 0.27064577 | E20: =(E8-E9)/E8 -> 0.28871517 | F20: =(F8-F9)/F8 -> 0.26305788
A21: Capex as % of Revenue | B21: =B14/B5 -> 0.019421314 | C21: =C14/C5 -> 0.017716167 | D21: =D14/D5 -> 0.013941066 | E21: =E14/E5 -> 0.013104028 | F21: =F14/F5 -> 0.013881905
A23: Note: D&A and ΔNWC are not broken out cleanly in headline filings pulled here —
A24: pull the full cash flow statement (via data_pull.py) and update Assumptions tab with exact %s.

Sheet Assumptions
A1: Assumptions — every lever the model uses
A2: Edit ONLY here. Yellow = verify/refresh before trusting output.
A4: REVENUE & MARGIN FORECAST
A5: Revenue growth — Year 1 (FY27) | B5: 0.09 | C5: Close to FY26 actual growth (9.85%); fades after.
A6: Revenue growth — fades to by Year 5 (FY31) | B6: 0.07 | C6: Long-run IT services growth assumption for India, ~nominal GDP-plus.
A7: EBIT margin (held flat, all 5 years) | B7: 0.228 | C7: 5yr historical average EBIT margin (see Historicals row 19).
A8: Effective tax rate | B8: 0.27 | C8: ≈ FY22–26 average effective tax rate.
A9: D&A as % of revenue | B9: 0.028 | C9: Placeholder — replace with exact figure from cash flow statement.
A10: Capex as % of revenue | B10: 0.015 | C10: ≈ 5yr historical average (see Historicals row 21).
A11: Δ Net Working Capital as % of revenue change | B11: 0.1 | C11: Placeholder — Infosys has high receivables (~90+ days); verify from filings.
A13: WACC INPUTS
A14: Risk-free rate (India 10Y G-Sec yield) | B14: 0.069 | C14: REFRESH from investing.com / RBI before use.
A15: Equity risk premium (India) | B15: 0.065 | C15: REFRESH — see Damodaran's country ERP dataset (updated ~yearly).
A16: Beta (INFY vs NIFTY 50) | B16: 0.75 | C16: REFRESH — recompute from 2-5yr weekly returns, or pull via yfinance.
A17: Pre-tax cost of debt | B17: 0.07 | C17: REFRESH — interest expense ÷ total debt, latest annual report.
A19: VALUATION INPUTS
A20: Terminal growth rate | B20: 0.04 | C20: ≈ long-run India nominal GDP growth proxy.
A21: Current share price (₹) | B21: 1100 | C21: REFRESH — live NSE:INFY price.
A22: Shares outstanding (Crores) | B22: =Historicals!B16 -> 414
A23: Total debt, latest year (₹ Cr) | B23: =Historicals!F12 -> 3749
A24: Cash & equivalents, latest year (₹ Cr) | B24: =Historicals!F13 -> 8727
A25: BUY threshold (upside required) | B25: 0.15 | C25: Implied price > current price by this much -> BUY.
A26: SELL threshold (downside trigger) | B26: -0.15 | C26: Implied price below current price by this much -> SELL.

Sheet Forecast
A1: 5-Year Forecast — FY2027 to FY2031
A2: All figures in ₹ Crores. Every formula pulls from Assumptions tab.
A4: ₹ Crores | B4: FY2027 | C4: FY2028 | D4: FY2029 | E4: FY2030 | F4: FY2031
A5: Revenue growth % | B5: =Assumptions!$B$5 -> 0.09 | C5: =Assumptions!$B$5+(Assumptions!$B$6-Assumptions!$B$5)*1/4 -> 0.085 | D5: =Assumptions!$B$5+(Assumptions!$B$6-Assumptions!$B$5)*2/4 -> 0.08 | E5: =Assumptions!$B$5+(Assumptions!$B$6-Assumptions!$B$5)*3/4 -> 0.075 | F5: =Assumptions!$B$5+(Assumptions!$B$6-Assumptions!$B$5)*4/4 -> 0.07
A6: Revenue | B6: =Historicals!F5*(1+B5) -> 199439.48 | C6: =B6*(1+C5) -> 216391.84 | D6: =C6*(1+D5) -> 233703.18 | E6: =D6*(1+E5) -> 251230.92 | F6: =E6*(1+F5) -> 268817.09
A7: EBIT | B7: =B6*Assumptions!$B$7 -> 45472.201 | C7: =C6*Assumptions!$B$7 -> 49337.339 | D7: =D6*Assumptions!$B$7 -> 53284.326 | E7: =E6*Assumptions!$B$7 -> 57280.65 | F7: =F6*Assumptions!$B$7 -> 61290.296
A8: Tax on EBIT | B8: =B7*Assumptions!$B$8 -> 12277.494 | C8: =C7*Assumptions!$B$8 -> 13321.081 | D8: =D7*Assumptions!$B$8 -> 14386.768 | E8: =E7*Assumptions!$B$8 -> 15465.776 | F8: =F7*Assumptions!$B$8 -> 16548.38
A9: NOPAT (EBIT after tax) | B9: =B7-B8 -> 33194.707 | C9: =C7-C8 -> 36016.257 | D9: =D7-D8 -> 38897.558 | E9: =E7-E8 -> 41814.875 | F9: =F7-F8 -> 44741.916
A10: (+) D&A | B10: =B6*Assumptions!$B$9 -> 5584.3054 | C10: =C6*Assumptions!$B$9 -> 6058.9714 | D10: =D6*Assumptions!$B$9 -> 6543.6891 | E10: =E6*Assumptions!$B$9 -> 7034.4658 | F10: =F6*Assumptions!$B$9 -> 7526.8784
A11: (-) Capex | B11: =B6*Assumptions!$B$10 -> 2991.5922 | C11: =C6*Assumptions!$B$10 -> 3245.8775 | D11: =D6*Assumptions!$B$10 -> 3505.5477 | E11: =E6*Assumptions!$B$10 -> 3768.4638 | F11: =F6*Assumptions!$B$10 -> 4032.2563
A12: (-) Δ Net Working Capital | B12: =(B6-Historicals!F5)*Assumptions!$B$11 -> 1646.748 | C12: =(C6-B6)*Assumptions!$B$11 -> 1695.2356 | D12: =(D6-C6)*Assumptions!$B$11 -> 1731.1347 | E12: =(E6-D6)*Assumptions!$B$11 -> 1752.7739 | F12: =(F6-E6)*Assumptions!$B$11 -> 1758.6164
A13: Unlevered Free Cash Flow | B13: =B9+B10-B11-B12 -> 34140.672 | C13: =C9+C10-C11-C12 -> 37134.115 | D13: =D9+D10-D11-D12 -> 40204.564 | E13: =E9+E10-E11-E12 -> 43328.103 | F13: =F9+F10-F11-F12 -> 46477.921

Sheet WACC
A1: WACC — Weighted Average Cost of Capital
A2: CAPM for cost of equity; market-value weights.
A4: COST OF EQUITY (CAPM)
A5: Risk-free rate | B5: =Assumptions!B14 -> 0.069
A6: Equity risk premium | B6: =Assumptions!B15 -> 0.065
A7: Beta | B7: =Assumptions!B16 -> 0.75
A8: Cost of Equity = Rf + Beta x ERP | B8: =B5+B7*B6 -> 0.11775
A10: COST OF DEBT
A11: Pre-tax cost of debt | B11: =Assumptions!B17 -> 0.07
A12: Tax rate | B12: =Assumptions!B8 -> 0.27
A13: After-tax cost of debt | B13: =B11*(1-B12) -> 0.0511
A15: CAPITAL WEIGHTS
A16: Market cap (₹ Cr) = price x shares | B16: =Assumptions!B21*Assumptions!B22 -> 455400
A17: Total debt (₹ Cr) | B17: =Assumptions!B23 -> 3749
A18: Weight of equity | B18: =B16/(B16+B17) -> 0.99183489
A19: Weight of debt | B19: =B17/(B16+B17) -> 0.0081651054
A21: WACC | B21: =B18*B8+B19*B13 -> 0.1172058

Sheet DCF
A1: DCF — Implied Share Price & Recommendation
A2: Discounts Forecast!FCF at WACC; Gordon Growth terminal value.
A4: ₹ Crores | B4: FY2027 | C4: FY2028 | D4: FY2029 | E4: FY2030 | F4: FY2031
A5: Unlevered FCF | B5: =Forecast!B13 -> 34140.672 | C5: =Forecast!C13 -> 37134.115 | D5: =Forecast!D13 -> 40204.564 | E5: =Forecast!E13 -> 43328.103 | F5: =Forecast!F13 -> 46477.921
A6: Discount period (n) | B6: 1 | C6: 2 | D6: 3 | E6: 4 | F6: 5
A7: Discount factor = 1/(1+WACC)^n | B7: =1/(1+WACC!$B$21)^B6 -> 0.89509024 | C7: =1/(1+WACC!$B$21)^C6 -> 0.80118653 | D7: =1/(1+WACC!$B$21)^D6 -> 0.71713424 | E7: =1/(1+WACC!$B$21)^E6 -> 0.64189986 | F7: =1/(1+WACC!$B$21)^F6 -> 0.5745583
A8: PV of FCF | B8: =B5*B7 -> 30558.982 | C8: =C5*C7 -> 29751.353 | D8: =D5*D7 -> 28832.07 | E8: =E5*E7 -> 27812.303 | F8: =F5*F7 -> 26704.275
A10: TERMINAL VALUE (Gordon Growth)
A11: Terminal growth rate | B11: =Assumptions!B20 -> 0.04
A12: Terminal Value = FCF_Y5 x (1+g) / (WACC - g) | B12: =F5*(1+B11)/(WACC!$B$21-B11) -> 626080.44
A13: PV of Terminal Value | B13: =B12*F7 -> 359719.71
A15: VALUATION BRIDGE
A16: Sum of PV of FCF (Years 1-5) | B16: =SUM(B8:F8) -> 143658.98
A17: (+) PV of Terminal Value | B17: =B13 -> 359719.71
A18: Enterprise Value | B18: =B16+B17 -> 503378.69
A19: (-) Total Debt | B19: =Assumptions!B23 -> 3749
A20: (+) Cash & Equivalents | B20: =Assumptions!B24 -> 8727
A21: Equity Value | B21: =B18-B19+B20 -> 508356.69
A22: Shares Outstanding (Cr) | B22: =Assumptions!B22 -> 414
A24: OUTPUT
A25: IMPLIED SHARE PRICE (₹) | B25: =B21/B22 -> 1227.9147
A26: Current Share Price (₹) | B26: =Assumptions!B21 -> 1100
A27: Upside / (Downside) | B27: =B25/B26-1 -> 0.11628611
A28: RECOMMENDATION | B28: =IF(B27>Assumptions!B25,"BUY",IF(B27<Assumptions!B26,"SELL","HOLD")) -> HOLD
